UQLibrary/__init__.py
UQLibrary/__main__.py
UQLibrary/examples.py
UQLibrary/gsa.py
UQLibrary/lsa.py
UQLibrary/sampling.py
uqlibrary-0.1.3.dist-info/licenses/LICENSE
uqlibrary-0.1.3.dist-info/METADATA
uqlibrary-0.1.3.dist-info/WHEEL
uqlibrary-0.1.3.dist-info/top_level.txt
uqlibrary-0.1.3.dist-info/RECORD
