Metadata-Version: 2.4
Name: UQLibrary
Version: 0.1.3
Summary: Robust set of sensitivity and identifiability analysis methods.
Home-page: https://github.com/HarleyHanes/UQLibrary-CourseProject
Author: H. Hanes
Author-email: hhanes@ncsu.edu
License: LICENSE
Classifier: Programming Language :: Python :: 3
Classifier: License :: OSI Approved :: MIT License
Classifier: Operating System :: OS Independent
Requires-Python: >=3.8
License-File: LICENSE
Requires-Dist: numpy>=1.20.0
Requires-Dist: scipy>=1.7.1
Requires-Dist: matplotlib>=3.4.3
Requires-Dist: tabulate>=0.8.9
Requires-Dist: mpi4py>=3.1.3
Dynamic: author
Dynamic: author-email
Dynamic: classifier
Dynamic: description
Dynamic: description-content-type
Dynamic: home-page
Dynamic: license
Dynamic: license-file
Dynamic: requires-dist
Dynamic: requires-python
Dynamic: summary
